{
  "examId": 106,
  "examKey": "2017-635-F2",
  "subject": "Matemática A",
  "year": 2017,
  "phase": "F2",
  "groups": [
    {
      "id": 237,
      "name": "GRUPO I",
      "order": 0
    },
    {
      "id": 238,
      "name": "GRUPO II",
      "order": 1
    }
  ],
  "questions": [
    {
      "id": 1740,
      "question_number": "1",
      "statement": "1. Em C, conjunto dos números complexos, sejam z1 e z2 tais que zi 21 = + e zz i431 2# = −\nConsidere a condição zz zz12− = −\nMostre que o número complexo cis2 4\nr verifica esta condição e interprete geometricamente este facto.\nResolva este item sem recorrer à calculadora.",
      "question_type": "open",
      "max_points": null,
      "difficulty": null,
      "bloom_level": null,
      "topic": null,
      "subtopic": null,
      "estimated_minutes": null,
      "choices": null,
      "criteriaText": "1.º Processo\nDeterminar gxl^h , em função de k .................................................................. 5 pontos\nDeterminar g 1l^h , em função de k .................................................................. 3 pontos\nEscrever g 1 0=l^h ............................................................................................ 5 pontos\nObter o valor de k 1^h ...................................................................................... 2 pontos",
      "officialAnswer": null,
      "gabaritoDisponivel": true,
      "pontuacaoDisponivel": false,
      "statementCorrompido": false,
      "groupName": "GRUPO II",
      "contextTitle": null,
      "contextText": null
    },
    {
      "id": 1741,
      "question_number": "2",
      "statement": "2. Na Figura 3, está representado, num referencial o.n. Oxyz, o cubo ABCDEFGH6@\nSabe-se que:\n•  a face ABCD6@ está contida no plano xOy\n•  a aresta CD6@ está contida no eixo Oy\n•  o ponto D tem coordenadas ,,04 0^h\n•  o plano ACG é definido pela equação\nxy z 60+− − =",
      "question_type": "open",
      "max_points": null,
      "difficulty": null,
      "bloom_level": null,
      "topic": null,
      "subtopic": null,
      "estimated_minutes": null,
      "choices": null,
      "criteriaText": "2\na a aa a a+ = ++bl ............. 1 pontos\nEscrever cossen41 aa = .................................................................................... 3 pontos\nEscrever sen 2 2\n1a =^h ........................................................................................ 4 pontos\nEscrever ,sen kk k2 2",
      "officialAnswer": null,
      "gabaritoDisponivel": true,
      "pontuacaoDisponivel": false,
      "statementCorrompido": false,
      "groupName": "GRUPO II",
      "contextTitle": null,
      "contextText": null
    },
    {
      "id": 1742,
      "question_number": "3",
      "statement": "3. De uma função f , de domínio R, com derivada finita em todos os pontos do seu domínio, sabe-se\nque lim fx f\nxx\n2\n2 4\nx 2\n2\n−\n− =\n\" ^ ^h h\nQual é o valor de 'f 2^h ?",
      "question_type": "multiple_choice",
      "max_points": null,
      "difficulty": null,
      "bloom_level": null,
      "topic": null,
      "subtopic": null,
      "estimated_minutes": null,
      "choices": [
        {
          "id": 3110,
          "letter": "A",
          "text": "2 1−",
          "isCorrect": false
        },
        {
          "id": 3111,
          "letter": "B",
          "text": "4 1−",
          "isCorrect": false
        },
        {
          "id": 3112,
          "letter": "C",
          "text": "2 1",
          "isCorrect": false
        },
        {
          "id": 3113,
          "letter": "D",
          "text": "4 1",
          "isCorrect": false
        }
      ],
      "criteriaText": "3= −\n\" +\n^h ......................................................... 3 pontos\nConcluir que a reta de equação x 0= é assíntota vertical do gráfico\nde f ..................................................................................................................... 2 pontos\nDeterminar lim fx\nx \" 3+\n^h ..................................................................................... 3 pontos\nEscrever lim lim lnfx x\nx\nxx\n=\n\"\"33++\n^h ........................................... 1 pontos\nEscrever lim fx 0\nx\n=\n\" 3+\n^h ........................................................... 2 pontos\nConcluir que a reta de equação y 0= é assíntota horizontal do gráfico\nde f ..................................................................................................................... 2 pontos\nNota – Se for evidente a intenção de determinar lim fx\nx \" 3−\n^h ou lim fx\nx 0\" −\n^h , a\nclassificação a atribuir à resposta é desvalorizada em 2 pontos. Se, por\naplicação deste critério, o valor obtido for negativo, a resposta é classificada \ncom 0 pontos.",
      "officialAnswer": null,
      "gabaritoDisponivel": false,
      "pontuacaoDisponivel": false,
      "statementCorrompido": false,
      "groupName": "GRUPO I",
      "contextTitle": null,
      "contextText": null
    },
    {
      "id": 1743,
      "question_number": "4",
      "statement": "4. Considere a função f, de domínio +R , definida por lnfx x\nx=^h\nResolva os itens 4.1., 4.2. e 4.3. recorrendo a métodos analíticos, sem utilizar a calculadora.",
      "question_type": "open",
      "max_points": null,
      "difficulty": null,
      "bloom_level": null,
      "topic": null,
      "subtopic": null,
      "estimated_minutes": null,
      "choices": null,
      "criteriaText": null,
      "officialAnswer": null,
      "gabaritoDisponivel": false,
      "pontuacaoDisponivel": false,
      "statementCorrompido": false,
      "groupName": "GRUPO II",
      "contextTitle": null,
      "contextText": null
    },
    {
      "id": 1744,
      "question_number": "5",
      "statement": "5. Considere o desenvolvimento de cossenx x2\n2\na a+cm , em que e x 0R !!a\nDetermine os valores de a, pertencentes ao intervalo ,2rr 6@ , para os quais o termo independente \nde x, neste desenvolvimento, é igual a 1\nResolva este item recorrendo a métodos analíticos, sem utilizar a calculadora.",
      "question_type": "calculation",
      "max_points": null,
      "difficulty": null,
      "bloom_level": null,
      "topic": null,
      "subtopic": null,
      "estimated_minutes": null,
      "choices": null,
      "criteriaText": "5 2 Z+ 0 !a a r ra r r== + = +^h .......... 3 pontos\nObter os valores de e12",
      "officialAnswer": null,
      "gabaritoDisponivel": true,
      "pontuacaoDisponivel": false,
      "statementCorrompido": false,
      "groupName": "GRUPO II",
      "contextTitle": null,
      "contextText": null
    },
    {
      "id": 1745,
      "question_number": "6",
      "statement": "6. Num jardim, uma criança está a andar num baloiço cuja cadeira está suspensa por duas hastes rígidas. \nAtrás do baloiço, há um muro que limita esse jardim.\nA Figura 4 esquematiza a situação. O ponto P representa a posição da cadeira.\nP\nhaste\nmuro\nsolo\nd(t)\nFigura 4\nNum determinado instante, em que a criança está a dar balanço, é iniciada a contagem do tempo. Doze \nsegundos após esse instante, a criança deixa de dar balanço e procura parar o baloiço arrastando os pés \nno chão.\nAdmita que a distância, em decímetros, do ponto \nP ao muro, t segundos após o instante inicial, é dada \npor\nse\nse\nsen\nsen\ndt\ntt t\net t\n30 01 2\n30 12 12t12\n1#r\nr\n=\n+\n+ − $\n^\n^\n^\nh\nh\nh\n*\n(o argumento da função seno está expresso em radianos)",
      "question_type": "open",
      "max_points": null,
      "difficulty": null,
      "bloom_level": null,
      "topic": null,
      "subtopic": null,
      "estimated_minutes": null,
      "choices": null,
      "criteriaText": null,
      "officialAnswer": null,
      "gabaritoDisponivel": false,
      "pontuacaoDisponivel": false,
      "statementCorrompido": false,
      "groupName": "GRUPO II",
      "contextTitle": null,
      "contextText": null
    },
    {
      "id": 1746,
      "question_number": "7",
      "statement": "7. Considere, num referencial o.n. xOy, a região definida pela condição\nxy xy11 12 022 /#$+ + + ++^^ hh\nQual é o perímetro dessa região?",
      "question_type": "multiple_choice",
      "max_points": null,
      "difficulty": null,
      "bloom_level": null,
      "topic": null,
      "subtopic": null,
      "estimated_minutes": null,
      "choices": [
        {
          "id": 3126,
          "letter": "A",
          "text": "1r +",
          "isCorrect": false
        },
        {
          "id": 3127,
          "letter": "B",
          "text": "2 1r +",
          "isCorrect": false
        },
        {
          "id": 3128,
          "letter": "C",
          "text": "2r +",
          "isCorrect": false
        },
        {
          "id": 3129,
          "letter": "D",
          "text": "2 2r +",
          "isCorrect": false
        }
      ],
      "criteriaText": null,
      "officialAnswer": null,
      "gabaritoDisponivel": false,
      "pontuacaoDisponivel": false,
      "statementCorrompido": false,
      "groupName": "GRUPO I",
      "contextTitle": null,
      "contextText": null
    },
    {
      "id": 1747,
      "question_number": "8",
      "statement": "8. Seja un_i a sucessão definida por u 2\n1\nn\nn1\n=\n−\ncm\nQual das afirmações seguintes é verdadeira?",
      "question_type": "multiple_choice",
      "max_points": null,
      "difficulty": null,
      "bloom_level": null,
      "topic": null,
      "subtopic": null,
      "estimated_minutes": null,
      "choices": [
        {
          "id": 3130,
          "letter": "A",
          "text": "A sucessão un_i é uma progressão geométrica de razão 2 1",
          "isCorrect": false
        },
        {
          "id": 3131,
          "letter": "B",
          "text": "A sucessão un_i é uma progressão geométrica de razão 2",
          "isCorrect": false
        },
        {
          "id": 3132,
          "letter": "C",
          "text": "A sucessão un_i é uma progressão aritmética de razão 2 1",
          "isCorrect": false
        },
        {
          "id": 3133,
          "letter": "D",
          "text": "A sucessão un_i é uma progressão aritmética de razão 2",
          "isCorrect": false
        }
      ],
      "criteriaText": "8 × 5 pontos 40\nII 1. 2.1. 2.2. 2.3. 3.1. 3.2. 4.1. 4.2. 4.3. 5. 6.1. 6.2.",
      "officialAnswer": null,
      "gabaritoDisponivel": false,
      "pontuacaoDisponivel": false,
      "statementCorrompido": false,
      "groupName": "GRUPO I",
      "contextTitle": null,
      "contextText": null
    },
    {
      "id": 1750,
      "question_number": "2.2",
      "statement": "2.2. Seja r a reta definida pela condição xy z11− = − =\nDetermine as coordenadas do ponto de intersecção da reta r com o plano ACG",
      "question_type": "calculation",
      "max_points": null,
      "difficulty": null,
      "bloom_level": null,
      "topic": null,
      "subtopic": null,
      "estimated_minutes": null,
      "choices": null,
      "criteriaText": "2.2. ................................................................................................................................................. 10 pontos\nEste item pode ser resolvido por, pelo menos, três processos.",
      "officialAnswer": null,
      "gabaritoDisponivel": true,
      "pontuacaoDisponivel": false,
      "statementCorrompido": false,
      "groupName": "GRUPO II",
      "contextTitle": null,
      "contextText": null
    },
    {
      "id": 1751,
      "question_number": "2.3",
      "statement": "2.3. Seja P o vértice de uma pirâmide regular de base EFGH6@\nSabe-se que:\n•  a cota do ponto P é superior a 2\n•  o volume da pirâmide é 4\nDetermine a amplitude do ângulo OGP\nApresente o resultado em graus, arredondado às unidades.\nSe, em cálculos intermédios, proceder a arredondamentos, conserve, no mínimo, duas casas \ndecimais.\nA B\nCD\nE H\nGF\nx\ny\nz\nO\nFigura 3",
      "question_type": "calculation",
      "max_points": null,
      "difficulty": null,
      "bloom_level": null,
      "topic": null,
      "subtopic": null,
      "estimated_minutes": null,
      "choices": null,
      "criteriaText": "2.3. ................................................................................................................................................. 15 pontos\nDeterminar a altura da pirâmide .......................................................................... 2 pontos\nEscrever as coordenadas do ponto P ................................................................ 2 pontos\nEscrever as coordenadas do ponto G ............................................................... 1 pontos\nDeterminar as coordenadas do vetor GO ......................................................... 1 pontos\nDeterminar as coordenadas do vetor GP ......................................................... 1 pontos\nCalcular .GO GP .............................................................................................. 2 pontos\n\nDeterminar a norma do vetor GO ..................................................................... 1 pontos\nDeterminar a norma do vetor GP ...................................................................... 1 pontos\nEscrever a equação 2 cos OG P24 41 1##= `j W (ou equivalente) ............ 2 pontos\nObter a amplitude do ângulo OGP 85c^h (85°) .......................................................... 2 pontos",
      "officialAnswer": null,
      "gabaritoDisponivel": true,
      "pontuacaoDisponivel": false,
      "statementCorrompido": false,
      "groupName": "GRUPO II",
      "contextTitle": null,
      "contextText": null
    },
    {
      "id": 1752,
      "question_number": "3.1",
      "statement": "3.1. Escolhe-se, ao acaso, um aluno dessa escola.\nSeja A o acontecimento «o aluno escolhido é rapariga», e seja B o acontecimento «o aluno \nescolhido frequenta o 10.º ano».\nSabe-se que:\n•  a probabilidade de o aluno escolhido ser rapaz ou não frequentar o 10.º ano é 0,82\n•  a probabilidade de o aluno escolhido frequentar o 10.º ano, sabendo que é rapariga, é 3\n1\nDetermine P A^h",
      "question_type": "calculation",
      "max_points": null,
      "difficulty": null,
      "bloom_level": null,
      "topic": null,
      "subtopic": null,
      "estimated_minutes": null,
      "choices": null,
      "criteriaText": "3.1. ................................................................................................................................................. 15 pontos\nEscrever ,P AB 08 2, =^h .............................................................................. 3 pontos\nEscrever 3",
      "officialAnswer": null,
      "gabaritoDisponivel": true,
      "pontuacaoDisponivel": false,
      "statementCorrompido": false,
      "groupName": "GRUPO II",
      "contextTitle": null,
      "contextText": null
    },
    {
      "id": 1753,
      "question_number": "3.2",
      "statement": "3.2. Uma das turmas dessa escola tem trinta alunos, numerados de 1 a 30\nCom o objetivo de escolher quatro alunos dessa turma para formar uma comissão, introduzem-se, \nnum saco, trinta cartões, indistinguíveis ao tato, numerados de 1 a 30. Em seguida, retiram-se \nquatro cartões do saco, simultaneamente e ao acaso.\nQual é a probabilidade de os dois menores números saídos serem o 7 e o 22 ?\nApresente o resultado arredondado às milésimas.",
      "question_type": "open",
      "max_points": null,
      "difficulty": null,
      "bloom_level": null,
      "topic": null,
      "subtopic": null,
      "estimated_minutes": null,
      "choices": null,
      "criteriaText": "3.2. ................................................................................................................................................. 15 pontos\nEste item pode ser resolvido por, pelo menos, dois processos.",
      "officialAnswer": null,
      "gabaritoDisponivel": true,
      "pontuacaoDisponivel": false,
      "statementCorrompido": false,
      "groupName": "GRUPO II",
      "contextTitle": null,
      "contextText": null
    },
    {
      "id": 1755,
      "question_number": "4.3",
      "statement": "4.3. Para um certo número real k, a função g, de domínio +R , definida por gx x\nk fx= +^^ hh , tem\num extremo relativo para x 1=\nDetermine esse número k",
      "question_type": "calculation",
      "max_points": null,
      "difficulty": null,
      "bloom_level": null,
      "topic": null,
      "subtopic": null,
      "estimated_minutes": null,
      "choices": null,
      "criteriaText": "4.3. ................................................................................................................................................. 15 pontos\nEste item pode ser resolvido por, pelo menos, dois processos.",
      "officialAnswer": null,
      "gabaritoDisponivel": true,
      "pontuacaoDisponivel": false,
      "statementCorrompido": false,
      "groupName": "GRUPO II",
      "contextTitle": null,
      "contextText": null
    },
    {
      "id": 1758,
      "question_number": "6.1",
      "statement": "6.1. Determine, recorrendo à calculadora gráfica, o número de soluções da equação dt 27=^h no\nintervalo ,066@ , e interprete o resultado no contexto da situação descrita.\nNa sua resposta, reproduza, num referencial, o(s) gráfico(s) da(s) função(ões) visualizado(s) na \ncalculadora que lhe permite(m) resolver o problema.",
      "question_type": "calculation",
      "max_points": null,
      "difficulty": null,
      "bloom_level": null,
      "topic": null,
      "subtopic": null,
      "estimated_minutes": null,
      "choices": null,
      "criteriaText": "6.1. ................................................................................................................................................. 15 pontos\nEscrever sentt30 27r+ =^h (ou equivalente) ............................................... 2 pontos\nReproduzir o(s) gráfico(s) da função(ões) visualizado(s) na calculadora que\npermite(m) resolver a equação (ver nota) .......................................................... 4 pontos\nIndicar o número de soluções da equação d t 27 4=^^ hh .............................. 4 pontos\nInterpretar o resultado no contexto da situação descrita (Durante os primeiros \nseis segundos, a cadeira encontra-se por quatro vezes a uma distância de",
      "officialAnswer": null,
      "gabaritoDisponivel": true,
      "pontuacaoDisponivel": false,
      "statementCorrompido": false,
      "groupName": "GRUPO II",
      "contextTitle": null,
      "contextText": null
    },
    {
      "id": 1759,
      "question_number": "6.2",
      "statement": "6.2. Admita que, no instante em que é iniciada a contagem do tempo, as hastes do baloiço estão na \nvertical e que a distância do ponto P ao chão, nesse instante, é 4 dm\nTreze segundos e meio após o instante inicial, a distância do ponto P ao chão é 4,2 dm\nQual é o comprimento da haste?\nApresente o resultado em decímetros, arredondado às unidades.\nSe, em cálculos intermédios, proceder a arredondamentos, conserve, no mínimo, duas casas \ndecimais.\nFIM\n\nCOTAÇÕES\nGrupo Item\nCotação (em pontos)\nI 1. a 8.\n8 × 5 pontos 40\nII 1. 2.1. 2.2. 2.3. 3.1. 3.2. 4.1. 4.2. 4.3. 5. 6.1. 6.2.\n15 5 10 15 15 15 15 15 15 15 15 10 160\nTOTAL 200\n\nESTA PÁGINA NÃO ESTÁ IMPRESSA PROPOSITADAMENTE\n\nESTA PÁGINA NÃO ESTÁ IMPRESSA PROPOSITADAMENTE\n\nESTA PÁGINA NÃO ESTÁ IMPRESSA PROPOSITADAMENTE\n\nESTA PÁGINA NÃO ESTÁ IMPRESSA PROPOSITADAMENTE\n\nESTA PÁGINA NÃO ESTÁ IMPRESSA PROPOSITADAMENTE\n\nProva 635\n2.ª Fase\nVERSÃO 1",
      "question_type": "open",
      "max_points": null,
      "difficulty": null,
      "bloom_level": null,
      "topic": null,
      "subtopic": null,
      "estimated_minutes": null,
      "choices": null,
      "criteriaText": "6.2. ................................................................................................................................................. 10 pontos\nDeterminar d 0^h ................................................................................................ 1 pontos\nDeterminar ,d 13 5^h .......................................................................................... 1 pontos\nDeterminar ,dd01 35−^^ hh .............................................................................. 2 pontos\nEquacionar o problema ( , ,x x 02 272 2 2= − +^h 682 ou equivalente) .................. 3 pontos\nResolver a equação ............................................................................................ 2 pontos\nApresentar o comprimento da haste dm18^h ................................................... 1 pontos\nCOTAÇÕES\nGrupo Item\nCotação (em pontos)\nI 1. a 8.",
      "officialAnswer": null,
      "gabaritoDisponivel": true,
      "pontuacaoDisponivel": false,
      "statementCorrompido": false,
      "groupName": "GRUPO II",
      "contextTitle": null,
      "contextText": null
    }
  ]
}